cashifypythonetcd/__init__.py
cashifypythonetcd-0.0.1.dist-info/LICENSE
cashifypythonetcd-0.0.1.dist-info/METADATA
cashifypythonetcd-0.0.1.dist-info/WHEEL
cashifypythonetcd-0.0.1.dist-info/top_level.txt
cashifypythonetcd-0.0.1.dist-info/RECORD
